certify/__init__.py
certify/certify.py
certify_certbot-1.0.2.dist-info/LICENSE
certify_certbot-1.0.2.dist-info/METADATA
certify_certbot-1.0.2.dist-info/WHEEL
certify_certbot-1.0.2.dist-info/entry_points.txt
certify_certbot-1.0.2.dist-info/top_level.txt
certify_certbot-1.0.2.dist-info/RECORD
