Metadata-Version: 2.1
Name: certify-certbot
Version: 1.0.2
Summary: certbot command wrapper
Home-page: https://github.com/SiLeader/certify
Author: SiLeader
Author-email: sileader.dev@gmail.com
License: Apache License 2.0
Platform: UNKNOWN
Classifier: Environment :: Console
Classifier: Intended Audience :: Developers
Classifier: Intended Audience :: Information Technology
Classifier: Intended Audience :: System Administrators
Classifier: License :: OSI Approved
Classifier: License :: OSI Approved :: Apache Software License
